jure/__init__.py
jure/events.py
jure/handlers.py
jure/main.py
jure/utils.py
jure-0.3.1.dist-info/entry_points.txt
jure-0.3.1.dist-info/LICENSE
jure-0.3.1.dist-info/WHEEL
jure-0.3.1.dist-info/METADATA
jure-0.3.1.dist-info/RECORD
